Workbook

Sheet Assumptions
A1: Meesho fee assumptions — Goyal Lights
A2: Blue = input you can change. Every number here is an estimate from public 2026 fee guides; replace with the exact figures shown in your Supplier Panel → Payments → Fee Structure once your account is live.
A4: Shipping fee by packed weight (₹, forward, national average)
A5: Slab 1: up to 500 g | B5: 55 | C5: Public guides quote ₹35–65 for ≤500 g incl. zone mix; Meesho sets it per pincode, you cannot edit it
A6: Slab 2: 501–1000 g | B6: 80 | C6: Estimate
A7: Slab 3: 1001–2000 g | B7: 120 | C7: Estimate
A8: Slab 4: 2001–5000 g | B8: 220 | C8: Estimate; chandeliers land here
A9: GST on Meesho fees | B9: 0.18 | C9: 18% on shipping/return fees; you get input credit if GST-registered
A10: Return (customer) + RTO rate assumed — decor lights | B10: 0.1 | C10: Meesho lighting sellers report 8–15% under wrong/defective-only; higher under all-returns
A11: Return (customer) + RTO rate assumed — bulbs/technical | B11: 0.06 | C11: Lower change-of-mind
A12: Reverse shipping charge per returned parcel (₹) | B12: 70 | C12: Public guides: ₹40–165 depending on weight; ₹70 for sub-1 kg
A13: Share of returned items that are resaleable | B13: 0.6 | C13: Rest = loss (broken bulb, cut string)
A14: Packaging cost per order (₹, box + wrap + label) | B14: 12 | C14: S box; use 18 for M, 40 for L
A15: Meesho collection / platform fee % (if shown in your panel) | B15: 0 | C15: Meesho advertises 0% commission; some 2026 guides report a small collection fee — enter it if your panel shows one
A16: Target net margin on your cost (after all fees) | B16: 0.3 | C16: 30% is the floor for a Bhagirath Palace shop selling online; below 20% the returns eat it

Sheet Calculator
A1: SKU | B1: Type (Decor/Tech) | C1: Your cost ₹ | D1: Packed weight g | E1: Box (S/M/L) | F1: Shipping fee ₹ | G1: GST on fee ₹ | H1: Packaging ₹ | I1: Return rate | J1: Expected return cost ₹/order | K1: Platform fee ₹ | L1: Total cost per order ₹ | M1: Target margin ₹ | N1: Recommended Wrong/Defective price ₹ | O1: All-returns price ₹ (+12%) | P1: Suggested MRP ₹ (1.8x) | Q1: Net payout at recommended price ₹ | R1: Net margin % on cost | S1: Break-even price ₹
A2: GL-SL-10M | B2: Decor | C2: 55 | D2: 120 | E2: S | F2: =IF(D2<=500,Assumptions!$B$5,IF(D2<=1000,Assumptions!$B$6,IF(D2<=2000,Assumptions!$B$7,Assumptions!$B$8))) -> 55 | G2: =F2*Assumptions!$B$9 -> 9.9 | H2: =IF(E2="S",Assumptions!$B$14,IF(E2="M",Assumptions!$B$14*1.5,Assumptions!$B$14*3.3)) -> 12 | I2: =IF(B2="Decor",Assumptions!$B$10,Assumptions!$B$11) -> 0.1 | J2: =I2*(Assumptions!$B$12*(1+Assumptions!$B$9)+F2*(1+Assumptions!$B$9)+(1-Assumptions!$B$13)*C2) -> 16.95 | K2: =N2*Assumptions!$B$15 -> 0 | L2: =C2+F2+G2+H2+J2+K2 -> 148.85 | M2: =C2*Assumptions!$B$16 -> 16.5 | N2: =CEILING((C2+F2+G2+H2+J2+M2)/(1-Assumptions!$B$15),10)-1 -> 169 | O2: =CEILING(N2*1.12,10)-1 -> 189 | P2: =CEILING(N2*1.8,10)-1 -> 309 | Q2: =N2-F2-G2-H2-J2-K2 -> 75.15 | R2: =IF(C2=0,0,(Q2-C2)/C2) -> 0.36636364 | S2: =CEILING((C2+F2+G2+H2+J2)/(1-Assumptions!$B$15),1) -> 149
A3: GL-SL-20M | B3: Decor | C3: 85 | D3: 200 | E3: S | F3: =IF(D3<=500,Assumptions!$B$5,IF(D3<=1000,Assumptions!$B$6,IF(D3<=2000,Assumptions!$B$7,Assumptions!$B$8))) -> 55 | G3: =F3*Assumptions!$B$9 -> 9.9 | H3: =IF(E3="S",Assumptions!$B$14,IF(E3="M",Assumptions!$B$14*1.5,Assumptions!$B$14*3.3)) -> 12 | I3: =IF(B3="Decor",Assumptions!$B$10,Assumptions!$B$11) -> 0.1 | J3: =I3*(Assumptions!$B$12*(1+Assumptions!$B$9)+F3*(1+Assumptions!$B$9)+(1-Assumptions!$B$13)*C3) -> 18.15 | K3: =N3*Assumptions!$B$15 -> 0 | L3: =C3+F3+G3+H3+J3+K3 -> 180.05 | M3: =C3*Assumptions!$B$16 -> 25.5 | N3: =CEILING((C3+F3+G3+H3+J3+M3)/(1-Assumptions!$B$15),10)-1 -> 209 | O3: =CEILING(N3*1.12,10)-1 -> 239 | P3: =CEILING(N3*1.8,10)-1 -> 379 | Q3: =N3-F3-G3-H3-J3-K3 -> 113.95 | R3: =IF(C3=0,0,(Q3-C3)/C3) -> 0.34058824 | S3: =CEILING((C3+F3+G3+H3+J3)/(1-Assumptions!$B$15),1) -> 181
A4: GL-SL-30M | B4: Decor | C4: 110 | D4: 300 | E4: M | F4: =IF(D4<=500,Assumptions!$B$5,IF(D4<=1000,Assumptions!$B$6,IF(D4<=2000,Assumptions!$B$7,Assumptions!$B$8))) -> 55 | G4: =F4*Assumptions!$B$9 -> 9.9 | H4: =IF(E4="S",Assumptions!$B$14,IF(E4="M",Assumptions!$B$14*1.5,Assumptions!$B$14*3.3)) -> 18 | I4: =IF(B4="Decor",Assumptions!$B$10,Assumptions!$B$11) -> 0.1 | J4: =I4*(Assumptions!$B$12*(1+Assumptions!$B$9)+F4*(1+Assumptions!$B$9)+(1-Assumptions!$B$13)*C4) -> 19.15 | K4: =N4*Assumptions!$B$15 -> 0 | L4: =C4+F4+G4+H4+J4+K4 -> 212.05 | M4: =C4*Assumptions!$B$16 -> 33 | N4: =CEILING((C4+F4+G4+H4+J4+M4)/(1-Assumptions!$B$15),10)-1 -> 249 | O4: =CEILING(N4*1.12,10)-1 -> 279 | P4: =CEILING(N4*1.8,10)-1 -> 449 | Q4: =N4-F4-G4-H4-J4-K4 -> 146.95 | R4: =IF(C4=0,0,(Q4-C4)/C4) -> 0.33590909 | S4: =CEILING((C4+F4+G4+H4+J4)/(1-Assumptions!$B$15),1) -> 213
A5: GL-SL-30M-WW | B5: Decor | C5: 110 | D5: 300 | E5: M | F5: =IF(D5<=500,Assumptions!$B$5,IF(D5<=1000,Assumptions!$B$6,IF(D5<=2000,Assumptions!$B$7,Assumptions!$B$8))) -> 55 | G5: =F5*Assumptions!$B$9 -> 9.9 | H5: =IF(E5="S",Assumptions!$B$14,IF(E5="M",Assumptions!$B$14*1.5,Assumptions!$B$14*3.3)) -> 18 | I5: =IF(B5="Decor",Assumptions!$B$10,Assumptions!$B$11) -> 0.1 | J5: =I5*(Assumptions!$B$12*(1+Assumptions!$B$9)+F5*(1+Assumptions!$B$9)+(1-Assumptions!$B$13)*C5) -> 19.15 | K5: =N5*Assumptions!$B$15 -> 0 | L5: =C5+F5+G5+H5+J5+K5 -> 212.05 | M5: =C5*Assumptions!$B$16 -> 33 | N5: =CEILING((C5+F5+G5+H5+J5+M5)/(1-Assumptions!$B$15),10)-1 -> 249 | O5: =CEILING(N5*1.12,10)-1 -> 279 | P5: =CEILING(N5*1.8,10)-1 -> 449 | Q5: =N5-F5-G5-H5-J5-K5 -> 146.95 | R5: =IF(C5=0,0,(Q5-C5)/C5) -> 0.33590909 | S5: =CEILING((C5+F5+G5+H5+J5)/(1-Assumptions!$B$15),1) -> 213
A6: GL-SL-50M | B6: Decor | C6: 170 | D6: 480 | E6: M | F6: =IF(D6<=500,Assumptions!$B$5,IF(D6<=1000,Assumptions!$B$6,IF(D6<=2000,Assumptions!$B$7,Assumptions!$B$8))) -> 55 | G6: =F6*Assumptions!$B$9 -> 9.9 | H6: =IF(E6="S",Assumptions!$B$14,IF(E6="M",Assumptions!$B$14*1.5,Assumptions!$B$14*3.3)) -> 18 | I6: =IF(B6="Decor",Assumptions!$B$10,Assumptions!$B$11) -> 0.1 | J6: =I6*(Assumptions!$B$12*(1+Assumptions!$B$9)+F6*(1+Assumptions!$B$9)+(1-Assumptions!$B$13)*C6) -> 21.55 | K6: =N6*Assumptions!$B$15 -> 0 | L6: =C6+F6+G6+H6+J6+K6 -> 274.45 | M6: =C6*Assumptions!$B$16 -> 51 | N6: =CEILING((C6+F6+G6+H6+J6+M6)/(1-Assumptions!$B$15),10)-1 -> 329 | O6: =CEILING(N6*1.12,10)-1 -> 369 | P6: =CEILING(N6*1.8,10)-1 -> 599 | Q6: =N6-F6-G6-H6-J6-K6 -> 224.55 | R6: =IF(C6=0,0,(Q6-C6)/C6) -> 0.32088235 | S6: =CEILING((C6+F6+G6+H6+J6)/(1-Assumptions!$B$15),1) -> 275
A7: GL-PX-12M | B7: Decor | C7: 180 | D7: 350 | E7: M | F7: =IF(D7<=500,Assumptions!$B$5,IF(D7<=1000,Assumptions!$B$6,IF(D7<=2000,Assumptions!$B$7,Assumptions!$B$8))) -> 55 | G7: =F7*Assumptions!$B$9 -> 9.9 | H7: =IF(E7="S",Assumptions!$B$14,IF(E7="M",Assumptions!$B$14*1.5,Assumptions!$B$14*3.3)) -> 18 | I7: =IF(B7="Decor",Assumptions!$B$10,Assumptions!$B$11) -> 0.1 | J7: =I7*(Assumptions!$B$12*(1+Assumptions!$B$9)+F7*(1+Assumptions!$B$9)+(1-Assumptions!$B$13)*C7) -> 21.95 | K7: =N7*Assumptions!$B$15 -> 0 | L7: =C7+F7+G7+H7+J7+K7 -> 284.85 | M7: =C7*Assumptions!$B$16 -> 54 | N7: =CEILING((C7+F7+G7+H7+J7+M7)/(1-Assumptions!$B$15),10)-1 -> 339 | O7: =CEILING(N7*1.12,10)-1 -> 379 | P7: =CEILING(N7*1.8,10)-1 -> 619 | Q7: =N7-F7-G7-H7-J7-K7 -> 234.15 | R7: =IF(C7=0,0,(Q7-C7)/C7) -> 0.30083333 | S7: =CEILING((C7+F7+G7+H7+J7)/(1-Assumptions!$B$15),1) -> 285
A8: GL-CT-3X3 | B8: Decor | C8: 160 | D8: 420 | E8: M | F8: =IF(D8<=500,Assumptions!$B$5,IF(D8<=1000,Assumptions!$B$6,IF(D8<=2000,Assumptions!$B$7,Assumptions!$B$8))) -> 55 | G8: =F8*Assumptions!$B$9 -> 9.9 | H8: =IF(E8="S",Assumptions!$B$14,IF(E8="M",Assumptions!$B$14*1.5,Assumptions!$B$14*3.3)) -> 18 | I8: =IF(B8="Decor",Assumptions!$B$10,Assumptions!$B$11) -> 0.1 | J8: =I8*(Assumptions!$B$12*(1+Assumptions!$B$9)+F8*(1+Assumptions!$B$9)+(1-Assumptions!$B$13)*C8) -> 21.15 | K8: =N8*Assumptions!$B$15 -> 0 | L8: =C8+F8+G8+H8+J8+K8 -> 264.05 | M8: =C8*Assumptions!$B$16 -> 48 | N8: =CEILING((C8+F8+G8+H8+J8+M8)/(1-Assumptions!$B$15),10)-1 -> 319 | O8: =CEILING(N8*1.12,10)-1 -> 359 | P8: =CEILING(N8*1.8,10)-1 -> 579 | Q8: =N8-F8-G8-H8-J8-K8 -> 214.95 | R8: =IF(C8=0,0,(Q8-C8)/C8) -> 0.3434375 | S8: =CEILING((C8+F8+G8+H8+J8)/(1-Assumptions!$B$15),1) -> 265
A9: GL-RP-10M | B9: Decor | C9: 220 | D9: 900 | E9: M | F9: =IF(D9<=500,Assumptions!$B$5,IF(D9<=1000,Assumptions!$B$6,IF(D9<=2000,Assumptions!$B$7,Assumptions!$B$8))) -> 80 | G9: =F9*Assumptions!$B$9 -> 14.4 | H9: =IF(E9="S",Assumptions!$B$14,IF(E9="M",Assumptions!$B$14*1.5,Assumptions!$B$14*3.3)) -> 18 | I9: =IF(B9="Decor",Assumptions!$B$10,Assumptions!$B$11) -> 0.1 | J9: =I9*(Assumptions!$B$12*(1+Assumptions!$B$9)+F9*(1+Assumptions!$B$9)+(1-Assumptions!$B$13)*C9) -> 26.5 | K9: =N9*Assumptions!$B$15 -> 0 | L9: =C9+F9+G9+H9+J9+K9 -> 358.9 | M9: =C9*Assumptions!$B$16 -> 66 | N9: =CEILING((C9+F9+G9+H9+J9+M9)/(1-Assumptions!$B$15),10)-1 -> 429 | O9: =CEILING(N9*1.12,10)-1 -> 489 | P9: =CEILING(N9*1.8,10)-1 -> 779 | Q9: =N9-F9-G9-H9-J9-K9 -> 290.1 | R9: =IF(C9=0,0,(Q9-C9)/C9) -> 0.31863636 | S9: =CEILING((C9+F9+G9+H9+J9)/(1-Assumptions!$B$15),1) -> 359
A10: GL-DY-3M | B10: Decor | C10: 70 | D10: 220 | E10: S | F10: =IF(D10<=500,Assumptions!$B$5,IF(D10<=1000,Assumptions!$B$6,IF(D10<=2000,Assumptions!$B$7,Assumptions!$B$8))) -> 55 | G10: =F10*Assumptions!$B$9 -> 9.9 | H10: =IF(E10="S",Assumptions!$B$14,IF(E10="M",Assumptions!$B$14*1.5,Assumptions!$B$14*3.3)) -> 12 | I10: =IF(B10="Decor",Assumptions!$B$10,Assumptions!$B$11) -> 0.1 | J10: =I10*(Assumptions!$B$12*(1+Assumptions!$B$9)+F10*(1+Assumptions!$B$9)+(1-Assumptions!$B$13)*C10) -> 17.55 | K10: =N10*Assumptions!$B$15 -> 0 | L10: =C10+F10+G10+H10+J10+K10 -> 164.45 | M10: =C10*Assumptions!$B$16 -> 21 | N10: =CEILING((C10+F10+G10+H10+J10+M10)/(1-Assumptions!$B$15),10)-1 -> 189 | O10: =CEILING(N10*1.12,10)-1 -> 219 | P10: =CEILING(N10*1.8,10)-1 -> 349 | Q10: =N10-F10-G10-H10-J10-K10 -> 94.55 | R10: =IF(C10=0,0,(Q10-C10)/C10) -> 0.35071429 | S10: =CEILING((C10+F10+G10+H10+J10)/(1-Assumptions!$B$15),1) -> 165
A11: GL-FY-3M-BAT | B11: Decor | C11: 45 | D11: 90 | E11: S | F11: =IF(D11<=500,Assumptions!$B$5,IF(D11<=1000,Assumptions!$B$6,IF(D11<=2000,Assumptions!$B$7,Assumptions!$B$8))) -> 55 | G11: =F11*Assumptions!$B$9 -> 9.9 | H11: =IF(E11="S",Assumptions!$B$14,IF(E11="M",Assumptions!$B$14*1.5,Assumptions!$B$14*3.3)) -> 12 | I11: =IF(B11="Decor",Assumptions!$B$10,Assumptions!$B$11) -> 0.1 | J11: =I11*(Assumptions!$B$12*(1+Assumptions!$B$9)+F11*(1+Assumptions!$B$9)+(1-Assumptions!$B$13)*C11) -> 16.55 | K11: =N11*Assumptions!$B$15 -> 0 | L11: =C11+F11+G11+H11+J11+K11 -> 138.45 | M11: =C11*Assumptions!$B$16 -> 13.5 | N11: =CEILING((C11+F11+G11+H11+J11+M11)/(1-Assumptions!$B$15),10)-1 -> 159 | O11: =CEILING(N11*1.12,10)-1 -> 179 | P11: =CEILING(N11*1.8,10)-1 -> 289 | Q11: =N11-F11-G11-H11-J11-K11 -> 65.55 | R11: =IF(C11=0,0,(Q11-C11)/C11) -> 0.45666667 | S11: =CEILING((C11+F11+G11+H11+J11)/(1-Assumptions!$B$15),1) -> 139
A12: GL-BLB-9W-4 | B12: Tech | C12: 120 | D12: 220 | E12: S | F12: =IF(D12<=500,Assumptions!$B$5,IF(D12<=1000,Assumptions!$B$6,IF(D12<=2000,Assumptions!$B$7,Assumptions!$B$8))) -> 55 | G12: =F12*Assumptions!$B$9 -> 9.9 | H12: =IF(E12="S",Assumptions!$B$14,IF(E12="M",Assumptions!$B$14*1.5,Assumptions!$B$14*3.3)) -> 12 | I12: =IF(B12="Decor",Assumptions!$B$10,Assumptions!$B$11) -> 0.06 | J12: =I12*(Assumptions!$B$12*(1+Assumptions!$B$9)+F12*(1+Assumptions!$B$9)+(1-Assumptions!$B$13)*C12) -> 11.73 | K12: =N12*Assumptions!$B$15 -> 0 | L12: =C12+F12+G12+H12+J12+K12 -> 208.63 | M12: =C12*Assumptions!$B$16 -> 36 | N12: =CEILING((C12+F12+G12+H12+J12+M12)/(1-Assumptions!$B$15),10)-1 -> 249 | O12: =CEILING(N12*1.12,10)-1 -> 279 | P12: =CEILING(N12*1.8,10)-1 -> 449 | Q12: =N12-F12-G12-H12-J12-K12 -> 160.37 | R12: =IF(C12=0,0,(Q12-C12)/C12) -> 0.33641667 | S12: =CEILING((C12+F12+G12+H12+J12)/(1-Assumptions!$B$15),1) -> 209
A13: GL-BLB-9W-10 | B13: Tech | C13: 290 | D13: 520 | E13: M | F13: =IF(D13<=500,Assumptions!$B$5,IF(D13<=1000,Assumptions!$B$6,IF(D13<=2000,Assumptions!$B$7,Assumptions!$B$8))) -> 80 | G13: =F13*Assumptions!$B$9 -> 14.4 | H13: =IF(E13="S",Assumptions!$B$14,IF(E13="M",Assumptions!$B$14*1.5,Assumptions!$B$14*3.3)) -> 18 | I13: =IF(B13="Decor",Assumptions!$B$10,Assumptions!$B$11) -> 0.06 | J13: =I13*(Assumptions!$B$12*(1+Assumptions!$B$9)+F13*(1+Assumptions!$B$9)+(1-Assumptions!$B$13)*C13) -> 17.58 | K13: =N13*Assumptions!$B$15 -> 0 | L13: =C13+F13+G13+H13+J13+K13 -> 419.98 | M13: =C13*Assumptions!$B$16 -> 87 | N13: =CEILING((C13+F13+G13+H13+J13+M13)/(1-Assumptions!$B$15),10)-1 -> 509 | O13: =CEILING(N13*1.12,10)-1 -> 579 | P13: =CEILING(N13*1.8,10)-1 -> 919 | Q13: =N13-F13-G13-H13-J13-K13 -> 379.02 | R13: =IF(C13=0,0,(Q13-C13)/C13) -> 0.30696552 | S13: =CEILING((C13+F13+G13+H13+J13)/(1-Assumptions!$B$15),1) -> 420
... A20: GL-STR-5M-WW | B20: Tech | C20: 110 | D20: 260 | E20: S | F20: =IF(D20<=500,Assumptions!$B$5,IF(D20<=1000,Assumptions!$B$6,IF(D20<=2000,Assumptions!$B$7,Assumptions!$B$8))) -> 55 | G20: =F20*Assumptions!$B$9 -> 9.9 | H20: =IF(E20="S",Assumptions!$B$14,IF(E20="M",Assumptions!$B$14*1.5,Assumptions!$B$14*3.3)) -> 12 | I20: =IF(B20="Decor",Assumptions!$B$10,Assumptions!$B$11) -> 0.06 | J20: =I20*(Assumptions!$B$12*(1+Assumptions!$B$9)+F20*(1+Assumptions!$B$9)+(1-Assumptions!$B$13)*C20) -> 11.49 | K20: =N20*Assumptions!$B$15 -> 0 | L20: =C20+F20+G20+H20+J20+K20 -> 198.39 | M20: =C20*Assumptions!$B$16 -> 33 | N20: =CEILING((C20+F20+G20+H20+J20+M20)/(1-Assumptions!$B$15),10)-1 -> 239 | O20: =CEILING(N20*1.12,10)-1 -> 269 | P20: =CEILING(N20*1.8,10)-1 -> 439 | Q20: =N20-F20-G20-H20-J20-K20 -> 150.61 | R20: =IF(C20=0,0,(Q20-C20)/C20) -> 0.36918182 | S20: =CEILING((C20+F20+G20+H20+J20)/(1-Assumptions!$B$15),1) -> 199
A22: How to read this sheet
A23: • Yellow = fill in: your buying cost, the weight of the PACKED box (weigh it), and box size. Costs shown are placeholder guesses from Bhagirath Palace wholesale rates in Aug 2026 — replace every one.
A24: • Recommended Wrong/Defective price is the price you enter in the catalog under 'Only wrong/defective returns'. It covers shipping, GST on fees, packaging, expected return losses and your target margin, rounded to end in 9.
A25: • All-returns price is what to enter if you choose 'All returns' instead — 12% higher to cover the extra returns. Do not enter both; Meesho shows one price per return option.
A26: • MRP must be printed on the carton. If the carton MRP is lower than the suggested MRP, use the carton's. Meesho price can never exceed MRP.
A27: • Break-even price is the price at which you make zero after all fees. Never run a Meesho Ad or a sale below it.
A28: • Shipping fee here is a national average estimate. The real fee is per order (pincode + weight) and appears in the order payout. After 20 orders, average your real fees and update Assumptions B5:B8.
